abyssinica/__init__.py
abyssinica/calendar.py
abyssinica/numerals.py
abyssinica/romanization.py
abyssinica-2.0.0.dist-info/LICENSE
abyssinica-2.0.0.dist-info/METADATA
abyssinica-2.0.0.dist-info/WHEEL
abyssinica-2.0.0.dist-info/top_level.txt
abyssinica-2.0.0.dist-info/RECORD
