Metadata-Version: 2.1
Name: abyssinica
Version: 2.0.0
Summary: Locale functions for the countries of Eritrea and Ethiopia.
Home-page: https://github.com/ebenh/abyssinica/
Author: Ebenezer Hailemariam
Author-email: eben@derso.org
License: MIT License
Classifier: Intended Audience :: Developers
Classifier: License :: OSI Approved :: MIT License
Classifier: Operating System :: OS Independent
Classifier: Programming Language :: Python
Classifier: Programming Language :: Python :: 3
Classifier: Programming Language :: Python :: 3 :: Only
Classifier: Programming Language :: Python :: 3.6
Classifier: Programming Language :: Python :: 3.7
Classifier: Programming Language :: Python :: 3.8
Classifier: Topic :: Software Development :: Localization
Classifier: Topic :: Software Development :: Internationalization
Requires-Python: >=3.6
License-File: LICENSE
